{"stats":{"minecraft:dropped":{"minecraft:golden_boots":1,"minecraft:poisonous_potato":1,"minecraft:filled_map":2,"minecraft:shield":2,"minecraft:iron_leggings":2},"minecraft:custom":{"minecraft:interact_with_furnace":39,"minecraft:interact_with_anvil":1,"minecraft:mob_kills":9,"minecraft:interact_with_crafting_table":9,"minecraft:interact_with_stonecutter":1,"minecraft:time_since_death":47837,"minecraft:sleep_in_bed":2,"minecraft:time_since_rest":47860,"minecraft:sprint_one_cm":65397,"minecraft:damage_taken":2322,"minecraft:walk_one_cm":103459,"minecraft:damage_blocked_by_shield":200,"minecraft:drop":8,"minecraft:damage_dealt":1921,"minecraft:swim_one_cm":26239,"minecraft:fly_one_cm":157031,"minecraft:open_chest":54,"minecraft:crouch_one_cm":22204,"minecraft:play_time":77952,"minecraft:deaths":6,"minecraft:sneak_time":5687,"minecraft:walk_under_water_one_cm":2612,"minecraft:boat_one_cm":516682,"minecraft:jump":869,"minecraft:walk_on_water_one_cm":4250,"minecraft:interact_with_smoker":15,"minecraft:total_world_time":77952,"minecraft:fall_one_cm":26718},"minecraft:killed_by":{"minecraft:piglin":1,"minecraft:piglin_brute":2},"minecraft:killed":{"minecraft:magma_cube":2,"minecraft:piglin":2,"minecraft:sheep":1,"minecraft:piglin_brute":2},"minecraft:crafted":{"minecraft:jungle_boat":1,"minecraft:baked_potato":45,"minecraft:iron_helmet":1,"minecraft:bucket":1,"minecraft:bread":13,"minecraft:air":0,"minecraft:jungle_planks":52,"minecraft:iron_boots":1,"minecraft:diamond_pickaxe":1,"minecraft:shield":2,"minecraft:stick":4,"minecraft:iron_ingot":8,"minecraft:gold_ingot":45,"minecraft:iron_leggings":1},"minecraft:mined":{"minecraft:blackstone":2,"minecraft:basalt":2,"minecraft:torch":1,"minecraft:short_grass":11,"minecraft:cracked_polished_blackstone_bricks":39,"minecraft:tall_grass":2,"minecraft:polished_blackstone_bricks":78,"minecraft:carrots":15,"minecraft:wheat":39,"minecraft:cobbled_deepslate":2,"minecraft:gold_block":6,"minecraft:coal_ore":2,"minecraft:potatoes":30,"minecraft:oak_log":4,"minecraft:netherrack":122,"minecraft:oak_leaves":23},"minecraft:picked_up":{"minecraft:wheat":39,"minecraft:jungle_boat":7,"minecraft:potato":117,"minecraft:gold_block":5,"minecraft:oak_log":4,"minecraft:shield":1,"minecraft:iron_leggings":1,"minecraft:blackstone":2,"minecraft:kelp":10,"minecraft:wheat_seeds":92,"minecraft:cobbled_deepslate":2,"minecraft:iron_ingot":62,"minecraft:stick":1,"minecraft:torch":1,"minecraft:poisonous_potato":1,"minecraft:polished_blackstone_bricks":72,"minecraft:carrot":56,"minecraft:diamond":4,"minecraft:cracked_polished_blackstone_bricks":33,"minecraft:oak_sapling":5,"minecraft:netherrack":121,"minecraft:coal":2},"minecraft:used":{"minecraft:wheat_seeds":64,"minecraft:water_bucket":65,"minecraft:baked_potato":17,"minecraft:shield":3,"minecraft:diamond_axe":9,"minecraft:jungle_boat":8,"minecraft:netherrack":113,"minecraft:polished_blackstone_bricks":25,"minecraft:iron_chestplate":1,"minecraft:carrot":1,"minecraft:deepslate_tiles":32,"minecraft:diamond_pickaxe":255,"minecraft:cracked_polished_blackstone_bricks":25,"minecraft:diamond_sword":31,"minecraft:oak_sapling":5,"minecraft:bucket":66,"minecraft:potato":14,"minecraft:cobbled_deepslate":169}},"DataVersion":3953}